{"name":"Social Media Links","tagline":"Social Media Buttons","body":"[![](https://dl.dropboxusercontent.com/u/200015521/Social%20Icon%20Links/eBay.png)](http://www.ebay.com/usr/cmcomponents13)  \r\n[![](https://dl.dropboxusercontent.com/u/200015521/Social%20Icon%20Links/Facebook.png)](https://www.facebook.com/CarloMoscatiello)  \r\n[![](https://dl.dropboxusercontent.com/u/200015521/Social%20Icon%20Links/360cities.png)](https://www.360cities.net/profile/carlomoscatiello)  \r\n[![](https://dl.dropboxusercontent.com/u/200015521/Social%20Icon%20Links/BatchGeo.png)](http://batchgeo.com/map/CarsLifeMap)  \r\n[![](https://dl.dropboxusercontent.com/u/200015521/Social%20Icon%20Links/Deezer.png)](http://www.deezer.com/profile/735350015)  \r\n[![](https://dl.dropboxusercontent.com/u/200015521/Social%20Icon%20Links/Giphy.png)](http://giphy.com/channel/cm85)  \r\n[![](https://dl.dropboxusercontent.com/u/200015521/Social%20Icon%20Links/GitHub.png)](https://github.com/cm85)  \r\n[![](https://dl.dropboxusercontent.com/u/200015521/Social%20Icon%20Links/Google.png)](https://plus.google.com/u/0/+CarloMoscatiello85)  \r\n[![](https://dl.dropboxusercontent.com/u/200015521/Social%20Icon%20Links/Instagram.png)](https://instagram.com/CarloMoscatiello)  \r\n[![](https://dl.dropboxusercontent.com/u/200015521/Social%20Icon%20Links/LinkedIn.png)](https://www.linkedin.com/in/carlomoscatiello)  \r\n[![](https://dl.dropboxusercontent.com/u/200015521/Social%20Icon%20Links/Panoramio.png)](http://www.panoramio.com/user/cm85)  \r\n[![](https://dl.dropboxusercontent.com/u/200015521/Social%20Icon%20Links/Peppinos.png)](http://www.peppinosonline.com/locations.html)  \r\n[![](https://dl.dropboxusercontent.com/u/200015521/Social%20Icon%20Links/Pinterest.png)](https://www.pinterest.com/CarloMoscatello)  \r\n[![](https://dl.dropboxusercontent.com/u/200015521/Social%20Icon%20Links/Smarterer.png)](http://smarterer.com/cm85)  \r\n[![](https://dl.dropboxusercontent.com/u/200015521/Social%20Icon%20Links/Twitter.png)](https://twitter.com/C4RLOM)  \r\n[![](https://dl.dropboxusercontent.com/u/200015521/Social%20Icon%20Links/YouTube.png)](https://www.youtube.com/user/CarlosCrazyClips)  \r\n[![](https://dl.dropboxusercontent.com/u/200015521/Social%20Icon%20Links/CM%20Components.png)](http://www.cmcomponents.com)  \r\n[![](\r\n\t\t\thttps://dl.dropboxusercontent.com/u/200015521/Social%20Icon%20Links/Wiki.png)](http://peppinos-italian-family-restaurants.wikia.com/wiki/Peppinos_Italian_Family_Restaurants_Wikia)\r\n","google":"UA-66616202-1","note":"Don't delete this file! It's used internally to help with page regeneration."}